{
  "name": "Rice University",
  "uuid": "c4f67518-1874-40b2-8143-ab66627bf6dc",
  "data": {
    "scattergrams": {
      "gpa": {
        "gpaCount": 12,
        "gpaSum": 48.88,
        "gpaAvg": 4.07,
        "gpaConvSum": 48.86,
        "gpaConvAvg": 4.07,
        "act": null,
        "sat": {
          "count": 0,
          "sum": 0,
          "avg": null,
          "gpaCount": 0,
          "gpaSum": 0,
          "gpaAvg": null,
          "gpaConvSum": 0,
          "gpaConvAvg": null,
          "apps": {
            "deniedRD": [
              {
                "currentStudent": false,
                "typeName": "RD",
                "actComposite": 0,
                "actCompositeStudent": 0,
                "highestComboSat": 1400,
                "studentSAT1600Composite": 1370,
                "gpa": 3.9
              },
              {
                "currentStudent": false,
                "typeName": "RD",
                "actComposite": 0,
                "actCompositeStudent": 0,
                "highestComboSat": 1440,
                "studentSAT1600Composite": 1440,
                "gpa": 4.1
              },
              {
                "currentStudent": false,
                "typeName": "RD",
                "actComposite": 0,
                "actCompositeStudent": 0,
                "highestComboSat": 1240,
                "studentSAT1600Composite": 1240,
                "gpa": 3.99
              }
            ],
            "deniedED": [
              {
                "currentStudent": false,
                "typeName": "ED",
                "actComposite": 0,
                "actCompositeStudent": 0,
                "highestComboSat": 1450,
                "studentSAT1600Composite": 1450,
                "gpa": 3.72
              },
              {
                "currentStudent": false,
                "typeName": "ED",
                "actComposite": 0,
                "actCompositeStudent": 0,
                "highestComboSat": 1390,
                "studentSAT1600Composite": 1390,
                "gpa": 3.84
              }
            ],
            "waitlistedUnknownRD": [
              {
                "currentStudent": false,
                "typeName": "RD",
                "actComposite": 0,
                "actCompositeStudent": 0,
                "highestComboSat": 1540,
                "studentSAT1600Composite": 1540,
                "gpa": 4.29
              },
              {
                "currentStudent": false,
                "typeName": "RD",
                "actComposite": 0,
                "actCompositeStudent": 0,
                "highestComboSat": 1500,
                "studentSAT1600Composite": 1500,
                "gpa": 4.21
              }
            ]
          }
        }
      },
      "weightedGpa": {
        "gpaCount": 12,
        "gpaSum": 48.88,
        "gpaAvg": 4.07,
        "gpaConvSum": 48.86,
        "gpaConvAvg": 4.07,
        "act": null,
        "sat": {
          "count": 0,
          "sum": 0,
          "avg": null,
          "gpaCount": 0,
          "gpaSum": 0,
          "gpaAvg": null,
          "gpaConvSum": 0,
          "gpaConvAvg": null,
          "apps": {
            "deniedRD": [
              {
                "currentStudent": false,
                "typeName": "RD",
                "actComposite": 0,
                "actCompositeStudent": 0,
                "highestComboSat": 1400,
                "studentSAT1600Composite": 1370,
                "gpa": 3.9
              },
              {
                "currentStudent": false,
                "typeName": "RD",
                "actComposite": 0,
                "actCompositeStudent": 0,
                "highestComboSat": 1440,
                "studentSAT1600Composite": 1440,
                "gpa": 4.1
              },
              {
                "currentStudent": false,
                "typeName": "RD",
                "actComposite": 0,
                "actCompositeStudent": 0,
                "highestComboSat": 1240,
                "studentSAT1600Composite": 1240,
                "gpa": 3.99
              }
            ],
            "deniedED": [
              {
                "currentStudent": false,
                "typeName": "ED",
                "actComposite": 0,
                "actCompositeStudent": 0,
                "highestComboSat": 1450,
                "studentSAT1600Composite": 1450,
                "gpa": 3.72
              },
              {
                "currentStudent": false,
                "typeName": "ED",
                "actComposite": 0,
                "actCompositeStudent": 0,
                "highestComboSat": 1390,
                "studentSAT1600Composite": 1390,
                "gpa": 3.84
              }
            ],
            "waitlistedUnknownRD": [
              {
                "currentStudent": false,
                "typeName": "RD",
                "actComposite": 0,
                "actCompositeStudent": 0,
                "highestComboSat": 1540,
                "studentSAT1600Composite": 1540,
                "gpa": 4.29
              },
              {
                "currentStudent": false,
                "typeName": "RD",
                "actComposite": 0,
                "actCompositeStudent": 0,
                "highestComboSat": 1500,
                "studentSAT1600Composite": 1500,
                "gpa": 4.21
              }
            ]
          }
        }
      }
    },
    "applicationStatistics": {
      "accepted": {
        "act": {
          "actComposite": null,
          "actEnglish": null,
          "actMath": null,
          "actReading": null,
          "actScience": null,
          "actWriting": null
        },
        "sat": {
          "satTotal": {
            "25": 1470,
            "75": 1535
          },
          "satMath": {
            "25": 745,
            "75": 770
          },
          "satReadingWriting": {
            "25": 735,
            "75": 770
          }
        },
        "gpa": {
          "25": 3.9450000000000003,
          "75": 4.295
        },
        "weightedGpa": {
          "25": 3.9450000000000003,
          "75": 4.295
        },
        "gpaConverted": {
          "25": 3.9450000000000003,
          "75": 4.29
        },
        "weightedGpaConverted": {
          "25": 3.9450000000000003,
          "75": 4.29
        }
      },
      "enrolled": {
        "act": {
          "actComposite": null,
          "actEnglish": null,
          "actMath": null,
          "actReading": null,
          "actScience": null,
          "actWriting": null
        },
        "sat": {
          "satTotal": null,
          "satMath": null,
          "satReadingWriting": null
        },
        "gpa": {},
        "weightedGpa": {},
        "gpaConverted": {},
        "weightedGpaConverted": {}
      }
    }
  }
}